Workbook

Sheet Assumptions
A1: AETHER — Pricing & Unit Economics Model
A2: Built from Aether_Feasibility_Study.docx Section 6 (revised, current-law baseline). Yellow cells are inputs — change them to re-run every downstream sheet.
A4: Assumption | B4: Value | C4: Source / note
A5: PEPM price (per employee per month) | B5: 10 | C5: Operating Plan Section 8
A6: Avg employees per customer (illustrative) | B6: 180 | C6: Operating Plan Section 9 illustrative firm
A7: Pay cycles per year | B7: 26 | C7: Biweekly, per Operating Plan Section 9
A8: Loaded admin hourly rate | B8: 45 | C8: Operating Plan Section 9
A9: Admin hours saved per cycle — low | B9: 3 | C9: Operating Plan Section 9
A10: Admin hours saved per cycle — high | B10: 6 | C10: Operating Plan Section 9
A11: State/training + R&D credits found per year — low | B11: 5000 | C11: Feasibility Study Section 6 — current-law baseline, WOTC excluded
A12: State/training + R&D credits found per year — high | B12: 25000 | C12: Feasibility Study Section 6 — current-law baseline, WOTC excluded
A13: WOTC upside if Congress renews — low | B13: 13000 | C13: Difference vs. original $18k-$60k illustrative range that included WOTC
A14: WOTC upside if Congress renews — high | B14: 35000 | C14: Difference vs. original $18k-$60k illustrative range that included WOTC
A15: WOTC renewed this year? (1 = yes, 0 = no) | B15: 0 | C15: Feasibility Study Section 4 — WOTC lapsed for new hires after 2025-12-31; set to 1 only once Congress actually renews it
A16: Aether credit-share take rate, year 1 | B16: 0.18 | C16: Operating Plan Section 8 — 15-20%, stepping down; 18% used as midpoint
... A20: Portfolio-level avg employees per customer | B20: 150 | C20: Matches Full Build Section 9's 200-customer / $3.6M ARR sketch — used only on the Portfolio sheet

Sheet Per-Customer Economics
A1: Illustrative Single Customer — Construction Firm
A2: Mirrors Operating Plan Section 9's 180-employee illustrative firm, rebuilt on the Feasibility Study's current-law credit baseline.
A4: Line | B4: Low | C4: High | D4: Note
A5: Employees | B5: =Assumptions!B6 -> 180 | C5: =Assumptions!B6 -> 180
A6: Aether software revenue (PEPM), annual | B6: =Assumptions!B5*B5*12 -> 21600 | C6: =Assumptions!B5*B5*12 -> 21600 | D6: Stands alone — does not include credit-share or EWA, per the source plan's own instruction.
A7: Credits found (customer value, current-law + contingent WOTC) | B7: =Assumptions!B11+Assumptions!B15*Assumptions!B13 -> 5000 | C7: =Assumptions!B12+Assumptions!B15*Assumptions!B14 -> 25000 | D7: Value to the CUSTOMER, not Aether revenue — see credit-share row below.
A8: Aether credit-share revenue, annual | B8: =B7*Assumptions!B16 -> 900 | C8: =C7*Assumptions!B16 -> 4500
A9: Admin time recovered (customer value), annual | B9: =Assumptions!B9*Assumptions!B7*Assumptions!B8 -> 3510 | C9: =Assumptions!B10*Assumptions!B7*Assumptions!B8 -> 7020
A10: One avoided quit (customer value, one-time) | B10: =Assumptions!B17 -> 8000 | C10: =Assumptions!B18 -> 15000
A12: TOTAL Aether revenue (software + credit share) | B12: =B6+B8 -> 22500 | C12: =C6+C8 -> 26100
A13: TOTAL customer-visible value (credits + admin time + one avoided quit) | B13: =B7+B9+B10 -> 16510 | C13: =C7+C9+C10 -> 47020
A14: Customer value delivered per $1 of software spend | B14: =B13/B6 -> 0.76435185 | C14: =C13/C6 -> 2.1768519 | D14: The actual sales number: how many dollars of value show up for every dollar of PEPM spend.

Sheet Portfolio ARR Scale
A1: Portfolio ARR at Scale
A2: The 200-customer row reproduces Full Build Section 9's own sketch ($3.6M software ARR at 200 customers averaging 150 employees) as a sanity check on this model.
A4: Customers | B4: Avg employees | C4: Software ARR | D4: Credit-share ARR — low | E4: Credit-share ARR — high | F4: Total Aether ARR — low | G4: Total Aether ARR — high
A5: 20 | B5: =Assumptions!B20 -> 150 | C5: =A5*B5*Assumptions!B5*12 -> 360000 | D5: =A5*Assumptions!B11*Assumptions!B16 -> 18000 | E5: =A5*Assumptions!B12*Assumptions!B16 -> 90000 | F5: =C5+D5 -> 378000 | G5: =C5+E5 -> 450000
A6: 50 | B6: =Assumptions!B20 -> 150 | C6: =A6*B6*Assumptions!B5*12 -> 900000 | D6: =A6*Assumptions!B11*Assumptions!B16 -> 45000 | E6: =A6*Assumptions!B12*Assumptions!B16 -> 225000 | F6: =C6+D6 -> 945000 | G6: =C6+E6 -> 1125000
A7: 100 | B7: =Assumptions!B20 -> 150 | C7: =A7*B7*Assumptions!B5*12 -> 1800000 | D7: =A7*Assumptions!B11*Assumptions!B16 -> 90000 | E7: =A7*Assumptions!B12*Assumptions!B16 -> 450000 | F7: =C7+D7 -> 1890000 | G7: =C7+E7 -> 2250000
A8: 200 | B8: =Assumptions!B20 -> 150 | C8: =A8*B8*Assumptions!B5*12 -> 3600000 | D8: =A8*Assumptions!B11*Assumptions!B16 -> 180000 | E8: =A8*Assumptions!B12*Assumptions!B16 -> 900000 | F8: =C8+D8 -> 3780000 | G8: =C8+E8 -> 4500000
A9: 500 | B9: =Assumptions!B20 -> 150 | C9: =A9*B9*Assumptions!B5*12 -> 9000000 | D9: =A9*Assumptions!B11*Assumptions!B16 -> 450000 | E9: =A9*Assumptions!B12*Assumptions!B16 -> 2250000 | F9: =C9+D9 -> 9450000 | G9: =C9+E9 -> 11250000
A10: 200-customer row should read ≈ $3,600,000 software ARR at the default 150-employee portfolio assumption — that's the built-in check.

Sheet Stage I Cash Needs
A1: Stage I Cash Needs (partial — fill in the blue cells)
A2: SOC 2 figures are independently verified (Feasibility Study Section 6, Aug 2026). Counsel, insurance, and the spine hire's compensation are market-dependent — fill in real quotes as they come in.
A4: Item | B4: Low | C4: High | D4: Note
A5: SOC 2 Type I (audit fee + tooling + internal hours) | B5: 20000 | C5: 60000 | D5: Feasibility Study Section 6 — verified this session
A6: SOC 2 Type II (additional, ~9-12 months out) | B6: 30000 | C6: 80000 | D6: Feasibility Study Section 6 — verified this session
A7: Employment-tax / fintech counsel retainer (fill in) | B7: 0 | C7: 0 | D7: Market-dependent — get a real quote, see 02-Company-Ops/00-entity-and-legal
A8: Cyber / E&O / crime insurance, annual (fill in) | B8: 0 | C8: 0 | D8: Market-dependent — see 02-Company-Ops/02-insurance-and-risk
A9: Payroll-operations 'spine' hire, annualized comp (fill in) | B9: 0 | C9: 0 | D9: Market-dependent — see 02-Company-Ops/04-hiring-and-team
A10: Embedded rail integration / setup fee (fill in) | B10: 0 | C10: 0 | D10: Depends on ADR 0001 outcome — see 03-Product-OS/docs/architecture-decision-records
A12: TOTAL Stage I cash needs (this list only — not exhaustive) | B12: =SUM(B5:B10) -> 50000 | C12: =SUM(C5:C10) -> 140000
